deep_dummy_maths-0.1.0.dist-info/METADATA
deep_dummy_maths-0.1.0.dist-info/WHEEL
deep_dummy_maths-0.1.0.dist-info/licenses/LICENSE
deep_dummy_maths/_core.pyi
deep_dummy_maths/__init__.py
deep_dummy_maths/my_maths.py
deep_dummy_maths/_core.abi3.so
deep_dummy_maths-0.1.0.dist-info/RECORD
