Metadata-Version: 2.4
Name: deep_dummy_maths
Version: 0.1.0
Classifier: Development Status :: 4 - Beta
Classifier: Programming Language :: Python
Requires-Dist: maturin>=1.8.2
License-File: LICENSE
Summary: A dummy library for mathematical functions created by Deependu Jha.
Keywords: maths,python,rust,maturin,pyo3
Home-Page: https://github.com/deependujha/Deep-Dummy-Maths/
Author: Deependu Jha <deependujha21@gmail.com>
Author-email: deependujha <deependujha21@gmail.com>
License: MIT
Requires-Python: >=3.9
Project-URL: Source Code, https://github.com/deependujha/Deep-Dummy-Maths/
